{"nome": "nand", "vdd": 0.7, "atrasoCC": 9.202851e-10, "entradas": ["a", "b"], "saidas": ["g1"], "nodos": [{"nome": "g1", "critico": {"corr": 5555, "orie": "rr", "nodo": "g1", "said": "g1", "val": [[1, 1]]}, "atraso": {"g1": 1111}, "lets": [{"corr": 2222, "orie": "ff", "nodo": "g1", "said": "g1", "val": [[0, 1]]}, {"corr": 1111, "orie": "rr", "nodo": "g1", "said": "g1", "val": [[1, 1]]}]}, {"nome": "i1", "critico": {"corr": 1111, "orie": "ff", "nodo": "i1", "said": "g1", "val": [[1, 0]]}, "atraso": {"g1": 1111}, "lets": [{"corr": 2222, "orie": "ff", "nodo": "i1", "said": "g1", "val": [[1, 0]]}, {"corr": 1111, "orie": "rr", "nodo": "i1", "said": "g1", "val": [[1, 1]]}]}]}